jaidegui/__init__.py
jaidegui/gui.py
jaidegui/Jaide GUI.py
jaidegui/jgui_widgets.py
jaidegui/module_locator.py
jaidegui/worker_thread.py
jaidegui-1.0.0.dist-info/DESCRIPTION.rst
jaidegui-1.0.0.dist-info/entry_points.txt
jaidegui-1.0.0.dist-info/METADATA
jaidegui-1.0.0.dist-info/metadata.json
jaidegui-1.0.0.dist-info/pbr.json
jaidegui-1.0.0.dist-info/RECORD
jaidegui-1.0.0.dist-info/top_level.txt
jaidegui-1.0.0.dist-info/WHEEL
