Metadata-Version: 2.0
Name: jaidegui
Version: 1.0.0
Summary: A graphical tool for manipulating Junos devices.
Home-page: https://github.com/NetworkAutomation/jaide-gui
Author: Nathan Printz <nkprintz@gmail.com> and Geoff Rhodes <geofflrhodes@gmail.com>
Author-email: nkprintz@gmail.com
License: GNU GPL
Keywords: networking junos juniper
Platform: UNKNOWN
Classifier: Development Status :: 5 - Production/Stable
Classifier: Intended Audience :: Information Technology
Classifier: Intended Audience :: Telecommunications Industry
Classifier: Intended Audience :: System Administrators
Classifier: Topic :: System :: Networking
Classifier: Topic :: System :: Systems Administration
Classifier: Topic :: Utilities
Classifier: License :: OSI Approved :: GNU General Public License v2 (GPLv2)
Classifier: Programming Language :: Python
Classifier: Programming Language :: Python :: 2
Classifier: Programming Language :: Python :: 2.7
Classifier: Natural Language :: English
Requires-Dist: jaide (>=2.0.0)
Requires-Dist: Pmw (>=1.3.3)
